snackabra/__init__.py
snackabra/crypto.py
snackabra-0.4.6.dist-info/LICENSE.md
snackabra-0.4.6.dist-info/METADATA
snackabra-0.4.6.dist-info/WHEEL
snackabra-0.4.6.dist-info/top_level.txt
snackabra-0.4.6.dist-info/RECORD
