Metadata-Version: 2.1
Name: snackabra
Version: 0.4.6
Summary: Snackabra Python Library (Utilities)
Home-page: https://github.com/snackabra/snackabra-pylib
Author: Peter Magnusson
Author-email: snackabra@protonmail.com
License: UNKNOWN
Project-URL: Bug Tracker, https://github.com/snackabra/snackabra-pylib/issues
Platform: UNKNOWN
Classifier: Programming Language :: Python :: 3
Classifier: License :: OSI Approved :: GNU General Public License v3 (GPLv3)
Classifier: Operating System :: OS Independent
Requires-Python: >=3.8
License-File: LICENSE.md
Requires-Dist: cryptography
Requires-Dist: jwcrypto
